LICENSE
README.md
pyproject.toml
setup.py
wiser/__init__.py
wiser/gcloud/__init__.py
wiser/gcloud/firestore/__init__.py
wiser/gcloud/firestore/connectors/__init__.py
wiser/gcloud/firestore/connectors/firestore_connector.py
wiser/gcloud/firestore/services/__init__.py
wiser/gcloud/firestore/services/firestore_service.py
wiser/gcloud/firestore/types/__init__.py
wiser/gcloud/firestore/types/collection.py
wiser/gcloud/firestore/types/document.py
wiser/gcloud/firestore/types/query.py
wiser_gcloud_firestore.egg-info/PKG-INFO
wiser_gcloud_firestore.egg-info/SOURCES.txt
wiser_gcloud_firestore.egg-info/dependency_links.txt
wiser_gcloud_firestore.egg-info/namespace_packages.txt
wiser_gcloud_firestore.egg-info/not-zip-safe
wiser_gcloud_firestore.egg-info/requires.txt
wiser_gcloud_firestore.egg-info/top_level.txt