Metadata-Version: 2.1
Name: wiser-gcloud-firestore
Version: 0.2.0
Summary: Google Cloud Firestore APIs for wiser package
Home-page: https://github.com/audax-tech/wiser-gcloud-firestore
Author: Nicola Massarenti
Author-email: nicola.massarenti@gmail.com
License: UNKNOWN
Project-URL: Bug Tracker, https://github.com/audax-tech/wiser-gcloud-firestore/issues
Platform: Posix; MacOS X; Windows
Classifier: Programming Language :: Python :: 3.8
Classifier: License :: OSI Approved :: MIT License
Classifier: Operating System :: OS Independent
Requires-Python: >=3.8
